kaa/__init__.py
kaa/authorization.py
kaa/cli.py
kaa/decorators.py
kaa/enums.py
kaa/exceptions.py
kaa/filters.py
kaa/kaa.py
kaa/kaa_definition.py
kaa/openapi.py
kaa/request.py
kaa/resources.py
kaa/response.py
kaa/server.py
kaa/watchers.py
kaa_rest_server-0.3.4.dist-info/LICENSE
kaa_rest_server-0.3.4.dist-info/METADATA
kaa_rest_server-0.3.4.dist-info/WHEEL
kaa_rest_server-0.3.4.dist-info/entry_points.txt
kaa_rest_server-0.3.4.dist-info/top_level.txt
kaa_rest_server-0.3.4.dist-info/RECORD
