Metadata-Version: 2.2
Name: kaa-rest-server
Version: 0.3.4
Summary: A very simple python REST server
Author-email: Francesc d'Assís Requesens i Roca <francesc.requesens@proton.me>
License: MIT License
Project-URL: Homepage, https://github.com/elpeix/kaa
Project-URL: Bug Reports, https://github.com/elpeix/kaa
Project-URL: Source, https://github.com/elpeix/kaa
Keywords: server,development
Classifier: Development Status :: 4 - Beta
Classifier: Intended Audience :: Developers
Classifier: Topic :: Software Development :: Build Tools
Classifier: Programming Language :: Python :: 3
Classifier: License :: OSI Approved :: MIT License
Classifier: Operating System :: OS Independent
Requires-Python: >=3.10
License-File: LICENSE
